qj/__init__.py
qj/qj.py
qj-1.0.2.dist-info/licenses/LICENSE
qj_global/__init__.py
qj-1.0.2.dist-info/METADATA
qj-1.0.2.dist-info/WHEEL
qj-1.0.2.dist-info/top_level.txt
qj-1.0.2.dist-info/RECORD
