Metadata-Version: 2.4
Name: qj
Version: 1.0.2
Summary: qj: logging designed for debugging.
Home-page: https://github.com/itfische/qj
Download-URL: https://github.com/itfische/qj/archive/1.0.2.tar.gz
Author: Ian Fischer
Author-email: itfische@gmail.com
License: Apache 2.0
License-File: LICENSE
Dynamic: author
Dynamic: author-email
Dynamic: description
Dynamic: description-content-type
Dynamic: download-url
Dynamic: home-page
Dynamic: license
Dynamic: license-file
Dynamic: summary
